sqlpygen/__init__.py
sqlpygen/ast.py
sqlpygen/cli.py
sqlpygen/codegen.py
sqlpygen/errors.py
sqlpygen/language_server.py
sqlpygen/parse_tree.py
sqlpygen/tree_sitter_bindings.py
sqlpygen/templates/sql_test_sqlite3.py.jinja2
sqlpygen/templates/sqlite3.py.jinja2
sqlpygen/tree-sitter-sqlpygen/src/parser.c
sqlpygen-3.0.0.dist-info/METADATA
sqlpygen-3.0.0.dist-info/WHEEL
sqlpygen-3.0.0.dist-info/entry_points.txt
sqlpygen-3.0.0.dist-info/top_level.txt
sqlpygen-3.0.0.dist-info/RECORD
