Metadata-Version: 2.1
Name: sqlpygen
Version: 3.0.0
Summary: Generate type annotated Python code from annotated SQL
Author-email: Parantapa Bhattacharya <pb@parantapa.net>
Project-URL: Homepage, http://github.com/parantapa/sqlpygen3
Classifier: Programming Language :: Python :: 3
Classifier: License :: OSI Approved :: MIT License
Classifier: Operating System :: OS Independent
Requires-Python: >=3.11
Requires-Dist: click
Requires-Dist: rich
Requires-Dist: attrs
Requires-Dist: tree-sitter
Requires-Dist: jinja2
Requires-Dist: pygls
Requires-Dist: platformdirs
